django_loki_logger/__init__.py
django_loki_logger/formatters.py
django_loki_logger/handlers.py
django_loki_logger-0.0.2.dist-info/LICENSE
django_loki_logger-0.0.2.dist-info/METADATA
django_loki_logger-0.0.2.dist-info/WHEEL
django_loki_logger-0.0.2.dist-info/top_level.txt
django_loki_logger-0.0.2.dist-info/RECORD
